kauripay/__init__.py
kauripay/api.py
kauripay/enums.py
kauripay/processing/__init__.py
kauripay/processing/currency.py
kauripay/processing/deposit.py
kauripay/processing/exchange.py
kauripay/processing/exchange_rate.py
kauripay/processing/internal_movement.py
kauripay/processing/invoice.py
kauripay/processing/orders.py
kauripay/processing/pair.py
kauripay/processing/user.py
kauripay/processing/withdrawal.py
kauri_finance_sdk-0.0.4.dist-info/METADATA
kauri_finance_sdk-0.0.4.dist-info/WHEEL
kauri_finance_sdk-0.0.4.dist-info/top_level.txt
kauri_finance_sdk-0.0.4.dist-info/RECORD
