Metadata-Version: 2.1
Name: kauri-finance-sdk
Version: 0.0.4
Summary: Kauri Finance Software Development Kit
Home-page: https://github.com/kaurifinance/python-sdk/
Author: Kauri Finance
Author-email: info@kauri.finance
License: MIT License
Keywords: SDK
Platform: UNKNOWN
Classifier: Programming Language :: Python :: 3
Classifier: License :: OSI Approved :: MIT License
Classifier: Operating System :: OS Independent
Requires-Python: >=3.5
Requires-Dist: certifi
Requires-Dist: requests
